pterradactyl/__init__.py
pterradactyl/__main__.py
pterradactyl/cli.py
pterradactyl/commands/__init__.py
pterradactyl/commands/base.py
pterradactyl/commands/dump.py
pterradactyl/commands/env.py
pterradactyl/commands/lookup.py
pterradactyl/commands/manifest.py
pterradactyl/commands/state.py
pterradactyl/config.py
pterradactyl/facter/__init__.py
pterradactyl/facter/arguments.py
pterradactyl/facter/base.py
pterradactyl/facter/environment.py
pterradactyl/facter/jinja.py
pterradactyl/facter/regex.py
pterradactyl/facter/shell.py
pterradactyl/facter/woops/manifest_path.py
pterradactyl/terraform/__init__.py
pterradactyl/terraform/config.py
pterradactyl/terraform/terraform.py
pterradactyl/terraform/variable_extractor.py
pterradactyl/util/__init__.py
pterradactyl/util/download.py
pterradactyl/util/filesystem.py
pterradactyl/util/package.py
pterradactyl/validator/__init__.py
pterradactyl/validator/base.py
pterradactyl/validator/version.py
pterradactyl-1.6.1.dist-info/LICENSE.md
pterradactyl-1.6.1.dist-info/METADATA
pterradactyl-1.6.1.dist-info/WHEEL
pterradactyl-1.6.1.dist-info/entry_points.txt
pterradactyl-1.6.1.dist-info/RECORD
