Metadata-Version: 2.1
Name: pterradactyl
Version: 1.6.1
Summary: hiera-inspired terraform wrapper
Home-page: https://github.com/Nike-Inc/pterradactyl
License: Apache-2.0
Author: Rob King
Author-email: rob.king@nike.com
Maintainer: Mohamed Abdul Huq Ismail
Maintainer-email: Abdul.Ismail@nike.com
Requires-Python: >=3.10.10,<4.0.0
Classifier: License :: OSI Approved :: Apache Software License
Classifier: Programming Language :: Python :: 3
Classifier: Programming Language :: Python :: 3.11
Requires-Dist: appdirs (>=1.4.4,<2.0.0)
Requires-Dist: jinja2 (>=3.1.2,<4.0.0)
Requires-Dist: jsonpath-ng (>=1.5.3,<2.0.0)
Requires-Dist: phiera (>=2.1.0,<3.0.0)
Requires-Dist: pyyaml (>=6.0.0,<7.0.0)
Requires-Dist: requests (>=2.31.0,<3.0.0)
Requires-Dist: semantic_version (>=2.10.0,<3.0.0)
Project-URL: Repository, https://github.com/Nike-Inc/pterradactyl
